{
  "1": [],
  "2": [
    "ゼロ",
    "カー",
    "ガム",
    "キロ",
    "キー",
    "ゼミ",
    "ソロ",
    "ダム",
    "デモ",
    "ドア",
    "ネガ",
    "バス",
    "バン",
    "バー",
    "パス",
    "パン",
    "ビル",
    "ピン",
    "プロ",
    "ベル",
    "ペア",
    "ペン",
    "ママ",
    "ミス",
    "ミリ",
    "メモ",
    "レジ",
    "トン",
    "エイ",
    "ガス",
    "ゴム"
  ],
  "3": [
    "ボタン",
    "アウト",
    "アップ",
    "アラブ",
    "アルミ",
    "アワー",
    "イエス",
    "インキ",
    "インク",
    "ウール",
    "オイル",
    "カット",
    "カップ",
    "カバー",
    "カメラ",
    "カラー",
    "カルテ",
    "カレー",
    "カード",
    "カーブ",
    "ガイド",
    "ギター",
    "クイズ",
    "クラス",
    "グラス",
    "グラフ",
    "グレー",
    "ケーキ",
    "ケース",
    "ゲスト",
    "ゲーム",
    "コック",
    "コップ",
    "コピー",
    "コース",
    "コーチ",
    "コート",
    "コード",
    "ゴール",
    "サイズ",
    "サイン",
    "サボる",
    "サラダ",
    "シック",
    "シャツ",
    "ショー",
    "シーツ",
    "シート",
    "ジャズ",
    "ジャム",
    "スキー",
    "スター",
    "スーツ",
    "スープ",
    "ズボン",
    "セット",
    "センス",
    "センチ",
    "セール",
    "ゼリー",
    "ソフト",
    "ソース",
    "タイア",
    "タイプ",
    "タイム",
    "タイヤ",
    "タイル",
    "タオル",
    "タワー",
    "ダイヤ",
    "ダウン",
    "ダブる",
    "ダブル",
    "ダンス",
    "ダンプ",
    "チップ",
    "チーズ",
    "チーム",
    "テスト",
    "テニス",
    "テレビ",
    "テント",
    "テンポ",
    "テープ",
    "テーマ",
    "データ",
    "デート",
    "トイレ",
    "トップ",
    "トーン",
    "ドライ",
    "ドラマ",
    "ドリル",
    "ドレス",
    "ナイフ",
    "ニュー",
    "ネット",
    "ノック",
    "ノート",
    "バイト",
    "バケツ",
    "バター",
    "バック",
    "バッグ",
    "バッジ",
    "バット",
    "バンド",
    "パイプ",
    "パンク",
    "パンツ",
    "パート",
    "ヒント",
    "ビデオ",
    "ビール",
    "ピアノ",
    "ピンク",
    "ファン",
    "フリー",
    "ブザー",
    "ブラシ",
    "ブルー",
    "ブログ",
    "ブーツ",
    "ブーム",
    "プラス",
    "プラン",
    "プール",
    "ベスト",
    "ベッド",
    "ベルト",
    "ベンチ",
    "ベース",
    "ペット",
    "ペンキ",
    "ペンチ",
    "ホテル",
    "ホース",
    "ホーム",
    "ホール",
    "ボルト",
    "ボーイ",
    "ボート",
    "ボール",
    "ポスト",
    "ポット",
    "ポンプ",
    "ポーズ",
    "マイク",
    "マウス",
    "マスク",
    "マーク",
    "ミシン",
    "ミセス",
    "ミラー",
    "ミルク",
    "ムード",
    "メール",
    "モダン",
    "モデル",
    "ヤング",
    "ヨット",
    "ライス",
    "ライト",
    "ラジオ",
    "ラベル",
    "ランチ",
    "ランプ",
    "リズム",
    "リボン",
    "ルーズ",
    "ルール",
    "レバー",
    "レベル",
    "レンジ",
    "レンズ",
    "レース",
    "ロビー",
    "ロープ",
    "ワイン",
    "ワット",
    "アジア",
    "クラブ",
    "ダース",
    "マッチ",
    "グラム",
    "ガラス",
    "ページ"
  ],
  "4": [
    "ジーパン",
    "アフリカ",
    "アイデア",
    "アイロン",
    "アクセル",
    "アドレス",
    "アパート",
    "アルカリ",
    "アルバム",
    "アンテナ",
    "イコール",
    "インテリ",
    "インフレ",
    "ウーマン",
    "エアコン",
    "エプロン",
    "エンジン",
    "オフィス",
    "オルガン",
    "オレンジ",
    "オーバー",
    "オープン",
    "カクテル",
    "カセット",
    "カロリー",
    "カーテン",
    "カーナビ",
    "ガソリン",
    "ガレージ",
    "キッチン",
    "キャッチ",
    "キャリア",
    "キャンプ",
    "ギャング",
    "クリック",
    "クリーム",
    "クレーン",
    "クーラー",
    "グランド",
    "グループ",
    "コメント",
    "コンパス",
    "コンビニ",
    "コーナー",
    "コーラス",
    "サイクル",
    "サイレン",
    "サンダル",
    "サンプル",
    "サークル",
    "サービス",
    "システム",
    "シナリオ",
    "シャワー",
    "ショック",
    "ショップ",
    "シリーズ",
    "シーズン",
    "ジャンプ",
    "ジャンボ",
    "ジャンル",
    "ジュース",
    "ジーンズ",
    "スイッチ",
    "スカート",
    "スカーフ",
    "スクール",
    "スケート",
    "スタイル",
    "スタジオ",
    "スタンド",
    "スタート",
    "スチーム",
    "ステレオ",
    "ステーキ",
    "ステージ",
    "ストップ",
    "ストレス",
    "ストロボ",
    "ストロー",
    "ストーブ",
    "スピーチ",
    "スピード",
    "スプーン",
    "スペース",
    "スポーツ",
    "スマート",
    "スライド",
    "スリッパ",
    "セックス",
    "セメント",
    "センター",
    "セーター",
    "ソックス",
    "ソファー",
    "タイトル",
    "タイマー",
    "タクシー",
    "タレント",
    "ダイヤル",
    "チェック",
    "チェンジ",
    "チャイム",
    "チャンス",
    "チョーク",
    "テキスト",
    "テーブル",
    "デザイン",
    "デザート",
    "デッサン",
    "デパート",
    "トラック",
    "トラブル",
    "トランプ",
    "トンネル",
    "ドライブ",
    "ナイター",
    "ナイロン",
    "ナプキン",
    "ナンバー",
    "ニコニコ",
    "ニュース",
    "ネクタイ",
    "ハンカチ",
    "ハンガー",
    "ハンサム",
    "ハンドル",
    "バイバイ",
    "バスてい",
    "バランス",
    "バーゲン",
    "パジャマ",
    "パソコン",
    "パターン",
    "パチンコ",
    "パトカー",
    "ヒーター",
    "ビジネス",
    "ビタミン",
    "ビニール",
    "ビールス",
    "ピストル",
    "ファイト",
    "ファイル",
    "フィルム",
    "フェリー",
    "フォーク",
    "フォーム",
    "フロント",
    "フワフワ",
    "ブラウス",
    "ブレーキ",
    "ブローチ",
    "プリント",
    "ベテラン",
    "ボーナス",
    "ポイント",
    "ポケット",
    "ポスター",
    "マイナス",
    "マスコミ",
    "マスター",
    "マフラー",
    "マラソン",
    "メディア",
    "メニュー",
    "メンバー",
    "メーカー",
    "メーター",
    "モニター",
    "モーター",
    "モーテル",
    "ユニーク",
    "ユーモア",
    "ライター",
    "ラケット",
    "リットル",
    "リビング",
    "リポート",
    "リモコン",
    "レコード",
    "レシート",
    "レジャー",
    "レッスン",
    "レディー",
    "レポート",
    "ロケット",
    "ロッカー",
    "ローマじ",
    "ワープロ",
    "アメリカ",
    "ラーメン",
    "コーヒー",
    "メートル"
  ],
  "5": [
    "ワイシャツ",
    "アイディア",
    "アクセント",
    "アナウンス",
    "アプローチ",
    "アマチュア",
    "アルコール",
    "アルバイト",
    "アレルギー",
    "アンケート",
    "アンコール",
    "イヤリング",
    "ウイスキー",
    "ウエイター",
    "エアメール",
    "エチケット",
    "エネルギー",
    "エレガント",
    "エンジニア",
    "オンライン",
    "オートバイ",
    "カテゴリー",
    "カムバック",
    "カメラマン",
    "カレンダー",
    "カンニング",
    "カーペット",
    "ガスレンジ",
    "キャプテン",
    "キャンセル",
    "キャンパス",
    "キーボード",
    "クラシック",
    "クリスマス",
    "クレジット",
    "コンクール",
    "コンサート",
    "コンセント",
    "コンタクト",
    "コンテスト",
    "サンキュー",
    "シャッター",
    "ジェットき",
    "ジャガいも",
    "ジャンパー",
    "スクリーン",
    "ストライキ",
    "スピーカー",
    "スプリング",
    "スラックス",
    "セクション",
    "セレモニー",
    "タイピスト",
    "タイミング",
    "タイムリー",
    "チャンネル",
    "テレックス",
    "ドライバー",
    "ドライヤー",
    "ナンセンス",
    "ニュアンス",
    "ネックレス",
    "ノイローゼ",
    "ハイキング",
    "バイオリン",
    "パイロット",
    "パスポート",
    "パーセント",
    "パーティー",
    "ピクニック",
    "ファスナー",
    "ファックス",
    "フィルター",
    "フライパン",
    "プレゼント",
    "プログラム",
    "ボイコット",
    "ボールペン",
    "ポジション",
    "マッサージ",
    "マンション",
    "マーケット",
    "メッセージ",
    "メロディー",
    "モノレール",
    "ランニング",
    "レギュラー",
    "レストラン",
    "レンタカー",
    "レントゲン",
    "ワンピース",
    "ヨーロッパ",
    "キログラム"
  ],
  "6": [
    "アクセサリー",
    "アナウンサー",
    "インストール",
    "インタビュー",
    "ウェートレス",
    "ウエートレス",
    "エレベーター",
    "オークション",
    "オーケストラ",
    "ガイドブック",
    "クリーニング",
    "コマーシャル",
    "コレクション",
    "コントラスト",
    "コントロール",
    "コンピュータ",
    "サラリーマン",
    "サンドイッチ",
    "シートベルト",
    "スケジュール",
    "ストッキング",
    "スポーツカー",
    "スーツケース",
    "ソフトウエア",
    "ダイヤグラム",
    "ダイヤモンド",
    "チームワーク",
    "テニスコート",
    "トレーニング",
    "ドライブイン",
    "ハンドバッグ",
    "ビルディング",
    "プラスチック",
    "ヘリコプター",
    "ベストセラー",
    "ホームページ",
    "ミスプリント",
    "ミュージック",
    "ユニフォーム",
    "レインコート",
    "ロマンチック",
    "ワイングラス",
    "コンクリート",
    "キロメートル"
  ],
  "7": [
    "アイスクリーム",
    "アドレスちょう",
    "インターネット",
    "インターフォン",
    "インフルエンザ",
    "エスカレーター",
    "オートマチック",
    "オーバーコート",
    "コンピューター",
    "コーヒーカップ",
    "サンタクロース",
    "ジャーナリスト",
    "スチュワーデス",
    "タイプライター",
    "デコレーション",
    "トランジスター",
    "ノートパソコン",
    "プラットホーム",
    "ラッシュアワー"
  ],
  "8": [
    "インターチェンジ",
    "オートメーション",
    "ガソリンスタンド",
    "キャッシュカード",
    "クレジットカード",
    "テープレコーダー",
    "レクリエーション"
  ],
  "9": [
    "インターナショナル",
    "インフォメーション",
    "オリエンテーション",
    "コミュニケーション",
    "ティッシュペーパー",
    "ドライクリーニング"
  ],
  "10": ["デモンストレーション"]
}
